[
    {
        "id": "CMT-001",
        "title": "Complete Dwarka drainage overhaul by Q2 2026",
        "announcedDate": "2025-08-15",
        "status": "delayed",
        "daysPending": 194,
        "linkedGrievanceIds": [
            "GRV-001"
        ],
        "riskLevel": "high"
    },
    {
        "id": "CMT-002",
        "title": "24x7 piped water supply to East Delhi wards",
        "announcedDate": "2025-06-01",
        "status": "in-progress",
        "daysPending": 269,
        "linkedGrievanceIds": [
            "GRV-002"
        ],
        "riskLevel": "medium"
    },
    {
        "id": "CMT-003",
        "title": "Completion of NH-48 service lane reconstruction",
        "announcedDate": "2025-04-10",
        "status": "stalled",
        "daysPending": 321,
        "linkedGrievanceIds": [
            "GRV-003"
        ],
        "riskLevel": "critical"
    },
    {
        "id": "CMT-004",
        "title": "Yamuna floodplain clean-up mission Phase 1",
        "announcedDate": "2025-10-02",
        "status": "not-started",
        "daysPending": 146,
        "linkedGrievanceIds": [
            "GRV-005"
        ],
        "riskLevel": "high"
    },
    {
        "id": "CMT-005",
        "title": "Digitize pension disbursement across all districts",
        "announcedDate": "2025-11-01",
        "status": "in-progress",
        "daysPending": 116,
        "linkedGrievanceIds": [
            "GRV-006"
        ],
        "riskLevel": "medium"
    },
    {
        "id": "CMT-006",
        "title": "Install crowd management systems at 5 metro stations",
        "announcedDate": "2025-09-15",
        "status": "in-progress",
        "daysPending": 163,
        "linkedGrievanceIds": [
            "GRV-004"
        ],
        "riskLevel": "low"
    },
    {
        "id": "CMT-007",
        "title": "Narela sewer network rehabilitation programme",
        "announcedDate": "2025-07-20",
        "status": "delayed",
        "daysPending": 220,
        "linkedGrievanceIds": [
            "GRV-016"
        ],
        "riskLevel": "high"
    },
    {
        "id": "CMT-008",
        "title": "Deploy additional DTC buses on Najafgarh route",
        "announcedDate": "2025-12-01",
        "status": "not-started",
        "daysPending": 86,
        "linkedGrievanceIds": [
            "GRV-021"
        ],
        "riskLevel": "medium"
    },
    {
        "id": "CMT-009",
        "title": "Drain desilting drive across South Delhi wards",
        "announcedDate": "2025-09-01",
        "status": "in-progress",
        "daysPending": 178,
        "linkedGrievanceIds": [
            "GRV-024"
        ],
        "riskLevel": "high"
    },
    {
        "id": "CMT-010",
        "title": "Emergency manhole cover replacement programme",
        "announcedDate": "2025-11-15",
        "status": "stalled",
        "daysPending": 102,
        "linkedGrievanceIds": [
            "GRV-030"
        ],
        "riskLevel": "critical"
    },
    {
        "id": "CMT-011",
        "title": "Sangam Vihar solid waste management upgrade",
        "announcedDate": "2025-08-01",
        "status": "delayed",
        "daysPending": 208,
        "linkedGrievanceIds": [
            "GRV-026"
        ],
        "riskLevel": "high"
    },
    {
        "id": "CMT-012",
        "title": "Mayur Vihar RO plant repair and commissioning",
        "announcedDate": "2025-12-15",
        "status": "in-progress",
        "daysPending": 72,
        "linkedGrievanceIds": [
            "GRV-028"
        ],
        "riskLevel": "medium"
    }
]